{
  "schemaVersion": "1.0.0",
  "id": "n_stride_periodic",
  "kind": "nonlinear_equation",
  "implementationId": "slip_quad_load.n_stride_periodic.explicit.v1",
  "implemented": true,
  "maturity": "experimental",
  "validationStatus": "tested",
  "provenance": {
    "sourceProblem": "single_stride",
    "sourceCommit": "19f3133073c988cc0c3424a647b4adbb60a90b99",
    "formulation": "per-stride contact constraints with final apex closure only"
  },
  "capabilities": {
    "simulate": true,
    "solve": true,
    "continue": false,
    "optimize": false,
    "visualize": true,
    "animate": true,
    "parameterHomotopy": false,
    "branchFamilyScan": false
  }
}
